[
  {
    "ID": "1a1e8af4b931",
    "createdAt": "Wed Nov 27 2024 14:39:23 GMT+0300 (GMT+03:00)",
    "updatedAt": "2024-12-02T10:18:58.631Z",
    "text": "menu link bir",
    "image": "apps/web/public/1715959332367_godiva-logo.svg",
    "image-alt": "image alt",
    "link": "/kampanya",
    "status": "draft",
    "scheduled": false
  },
  {
    "ID": "711e17caff62",
    "createdAt": "Wed Nov 27 2024 14:43:34 GMT+0300 (GMT+03:00)",
    "updatedAt": "2024-12-02T10:18:58.639Z",
    "text": "menu link dort",
    "image": "apps/web/public/1712564386732_pasabahce.svg",
    "image-alt": "alt",
    "link": "/makaron",
    "status": "draft",
    "scheduled": false
  },
  {
    "ID": "9d739387aae1",
    "createdAt": "Wed Nov 27 2024 14:41:38 GMT+0300 (GMT+03:00)",
    "updatedAt": "2024-12-02T10:18:58.647Z",
    "text": "menu link iki",
    "image": "apps/web/public/1717660995918_Bayram_Hediyeleri_2021.webp",
    "image-alt": "alt",
    "link": "/vazoda-cicek",
    "status": "draft",
    "scheduled": false
  },
  {
    "ID": "afb0355bc5e7",
    "createdAt": "Wed Nov 27 2024 14:42:48 GMT+0300 (GMT+03:00)",
    "updatedAt": "2024-12-02T10:18:58.658Z",
    "text": "menu link uc",
    "image": "apps/web/public/1711536237290_gubre-bnf-blog.jpg",
    "image-alt": "alt",
    "link": "/cicek-buketi/carnaval-rengarenk-gul-buketi",
    "status": "draft",
    "scheduled": false
  }
]