[
  {
    "name": "createdAt",
    "fieldId": "createdAt",
    "componentId": "date",
    "options": {},
    "validations": {
      "required-field": {
        "value": true
      }
    },
    "fieldType": "date",
    "system": true,
    "defaultField": false,
    "modelId": "custom-menu-items"
  },
  {
    "name": "updatedAt",
    "fieldId": "updatedAt",
    "componentId": "date",
    "options": {},
    "validations": {
      "required-field": {
        "value": true
      }
    },
    "fieldType": "date",
    "system": true,
    "defaultField": false,
    "modelId": "custom-menu-items"
  },
  {
    "name": "ID",
    "fieldId": "ID",
    "componentId": "single-line-text",
    "options": {},
    "validations": {
      "required-field": {
        "value": true
      }
    },
    "fieldType": "string",
    "system": true,
    "defaultField": false,
    "modelId": "custom-menu-items"
  },
  {
    "name": "status",
    "fieldId": "status",
    "componentId": "single-line-text",
    "options": {},
    "validations": {
      "required-field": {
        "value": true
      }
    },
    "fieldType": "string",
    "system": true,
    "defaultField": false,
    "modelId": "custom-menu-items"
  },
  {
    "name": "Text",
    "fieldId": "text",
    "modelId": "custom-menu-items",
    "componentId": "single-line-text",
    "options": {
    },
    "validations": {
    },
    "fieldType": "string"
  },
  {
    "name": "Image",
    "description": "Static image",
    "fieldId": "image",
    "modelId": "custom-menu-items",
    "componentId": "media",
    "options": {},
    "validations": {},
    "fieldType": "media"
  },
  {
    "name": "Image Alt",
    "fieldId": "image-alt",
    "modelId": "custom-menu-items",
    "componentId": "single-line-text",
    "options": {
    },
    "validations": {
    },
    "fieldType": "string"
  },
  {
    "name": "Link",
    "fieldId": "link",
    "modelId": "custom-menu-items",
    "componentId": "single-line-text",
    "options": {
    },
    "validations": {
    },
    "fieldType": "string"
  }
]
